corncobs-1.0.3.dist-info/METADATA
corncobs-1.0.3.dist-info/WHEEL
corncobs-1.0.3.dist-info/licenses/LICENSE.txt
corncobs/__init__.py
corncobs/_cobs.pyd
corncobs/_cobs.pyi
corncobs-1.0.3.dist-info/RECORD
