Metadata-Version: 2.4
Name: corncobs
Version: 1.0.3
Classifier: Programming Language :: Rust
Classifier: Programming Language :: Python :: Implementation :: CPython
License-File: LICENSE.txt
Summary: Consistent Overhead Byte Stuffing (COBS) backed by the corncobs Rust crate
License-Expression: MPL-2.0
Requires-Python: >=3.10
Project-URL: repository, https://github.com/ntamas/corncobs
